blendSupports/__init__.py
blendSupports/misc.py
blendSupports/Meshs/__init__.py
blendSupports/Meshs/graph_axis.py
blendSupports/Meshs/horizontal_dashed_line.py
blendSupports/Meshs/mesh_ref.py
blendSupports/Meshs/text.py
blendSupports/Nodes/__init__.py
blendSupports/Nodes/emission_node.py
blendSupports/Renders/__init__.py
blendSupports/Renders/render.py
blendSupports/Supports/__init__.py
blendSupports/Supports/collection_cleanup.py
blendSupports-0.7.1.dist-info/LICENSE
blendSupports-0.7.1.dist-info/METADATA
blendSupports-0.7.1.dist-info/WHEEL
blendSupports-0.7.1.dist-info/top_level.txt
blendSupports-0.7.1.dist-info/RECORD
